src/__init__.py
src/_version.py
src/diagnostics/horizon.py
src/models/__init__.py
src/models/base_model.py
src/models/hierarchical_bayes.py
src/models/improved_kalman.py
src/models/kalman_diffusion.py
src/models/poll_average.py
src/scripts/calibration_diagnostics.py
src/scripts/compare_models.py
src/scripts/generate_plots.py
src/scripts/horizon_diagnostics.py
src/scripts/per_state_calibration.py
src/scripts/per_state_calibration_plots.py
src/scripts/run_all.py
src/scripts/run_all_models.py
src/utils/__init__.py
src/utils/calibration.py
src/utils/data_utils.py
src/utils/logging_config.py
election_forecasting-0.1.1.dev17.dist-info/METADATA
election_forecasting-0.1.1.dev17.dist-info/WHEEL
election_forecasting-0.1.1.dev17.dist-info/entry_points.txt
election_forecasting-0.1.1.dev17.dist-info/licenses/LICENSE
election_forecasting-0.1.1.dev17.dist-info/RECORD
