Metadata-Version: 2.4
Name: election-forecasting
Version: 0.1.1.dev17
Summary: State-level presidential election forecasting models
Project-URL: Homepage, https://github.com/cmaloney111/election-forecasting-am215
Project-URL: Repository, https://github.com/cmaloney111/election-forecasting-am215
Project-URL: Documentation, https://election-forecasting-am215.readthedocs.io
Project-URL: Issues, https://github.com/cmaloney111/election-forecasting-am215/issues
Author-email: Cameron Maloney <cmaloney@g.harvard.edu>, Al Liu <aliuschaliu@college.harvard.edu>
License: MIT
License-File: LICENSE
Keywords: bayesian,election,forecasting,kalman-filter,polling
Classifier: License :: OSI Approved :: MIT License
Classifier: Programming Language :: Python :: 3
Classifier: Programming Language :: Python :: 3.9
Classifier: Programming Language :: Python :: 3.10
Classifier: Programming Language :: Python :: 3.11
Classifier: Programming Language :: Python :: 3.12
Classifier: Programming Language :: Python :: 3.13
Classifier: Topic :: Scientific/Engineering
Requires-Python: >=3.9
Requires-Dist: matplotlib>=3.7.0
Requires-Dist: numpy>=1.24.0
Requires-Dist: pandas>=2.0.0
Requires-Dist: rich>=14.2.0
Requires-Dist: scipy>=1.11.0
